{
  "type": "FeatureCollection",
  "name": "bynavne",
  "crs": { 
    "type": "name", 
    "properties": { 
      "name": "urn:ogc:def:crs:OGC:1.3:CRS84" 
    } 
  },
  "features": [
    {
      "type": "Feature",
      "properties": { 
        "text": "Kelstrup"
      },
      "geometry": { 
        "type": "Point", 
        "coordinates": [ 9.581994129, 55.196024757 ]
      }
    },
    {
      "type": "Feature", 
      "properties": {
        "text": "Maugstrup"
      },
      "geometry": {
        "type": "Point",
        "coordinates": [ 9.347733275, 55.292561338 ]
      }
    },
    {
      "type": "Feature",
      "properties": {
        "text": "Løgumgårde"
      },
      "geometry": {
        "type": "Point",
        "coordinates": [ 8.935372211, 55.087667407 ]
      }
    }
   ]
}
